{
    "@class": "com.kony.gen.viz.model.component.KVizLabel",
    "DNDConfig": null,
    "__parentReadjusting__": false,
    "_height_": {
        "type": "ref",
        "value": "preferred"
    },
    "_left_": {
        "type": "string",
        "value": "20px"
    },
    "_margin_": [
        1,
        1,
        1,
        1
    ],
    "_padding_": [
        0,
        0,
        0,
        0
    ],
    "_skin_": "safb4874e15c49a5bbe4959ab55f352e",
    "_text_": "Assign to",
    "_top_": {
        "type": "string",
        "value": "0px"
    },
    "_width_": {
        "type": "string",
        "value": "80%"
    },
    "_wrapping_": 2,
    "android": {
        "textStyle": {
            "letterSpacing": 0,
            "strikeThrough": false
        }
    },
    "canUpdateUI": true,
    "containerweight": 100,
    "contentalignment": 4,
    "id": "lblPopUpMainMessage",
    "info": null,
    "ipad": {
        "psp": {
            "wrapping": 2
        }
    },
    "iphone": {
        "psp": {
            "wrapping": 2
        }
    },
    "isvisible": true,
    "kuid": "ha1826012f0b4282a8ec12fb67ec1d0d",
    "name": "kony.ui.Label",
    "parent": "flxPopupHeader",
    "pf": "frmCSR",
    "texti18n": "i18n.frmCSR.lblPopUpMainMessage",
    "tooltip": "",
    "wType": "Label",
    "zindex": 1
}