{
    "@class": "com.kony.gen.viz.model.component.KVizLabel",
    "DNDConfig": null,
    "_height_": {
        "type": "ref",
        "value": "preferred"
    },
    "_margin_": [
        1,
        1,
        1,
        1
    ],
    "_padding_": [
        0,
        0,
        0,
        0
    ],
    "_skin_": "sc609830921249f09bc7b3b985ee2994",
    "_text_": "No search results were found. Refine the search criteria or ",
    "_top_": {
        "type": "string",
        "value": "110dp"
    },
    "_width_": {
        "type": "ref",
        "value": "preferred"
    },
    "_wrapping_": 2,
    "android": {
        "textStyle": {
            "letterSpacing": 0,
            "strikeThrough": false
        }
    },
    "canUpdateUI": true,
    "centerx": {
        "type": "string",
        "value": "47%"
    },
    "containerweight": 100,
    "contentalignment": 4,
    "id": "lblNoResult",
    "info": null,
    "ipad": {
        "psp": {
            "wrapping": 2
        }
    },
    "iphone": {
        "psp": {
            "wrapping": 2
        }
    },
    "iscustomlayout": false,
    "isvisible": true,
    "kuid": "c1bf734a91394d429695bb9fcc74a6e6",
    "name": "kony.ui.Label",
    "parent": "flxNoResultsFound",
    "pf": "userwidgetmodel",
    "retaincontentalignment": false,
    "retainflexpositionproperties": false,
    "texti18n": "i18n.frmCustomerManagementController.NoresultsSearchForaCustomer",
    "tooltip": "",
    "wType": "Label",
    "zindex": 1
}