{
    "DNDConfig": null,
    "__parentReadjusting__": false,
    "_height_": {
        "type": "string",
        "value": "30dp"
    },
    "_margin_": [
        0,
        0,
        0,
        0
    ],
    "_orientation_": 6,
    "_padding_": [
        0,
        0,
        0,
        0
    ],
    "_percent_": true,
    "_right_": {
        "type": "string",
        "value": "5px"
    },
    "_skin_": "s8ff24328417401b877c3ceb2a5fa27c",
    "_width_": {
        "type": "string",
        "value": "30px"
    },
    "allboxes": [],
    "autogrowmode": 0,
    "canUpdateUI": true,
    "centery": {
        "type": "string",
        "value": "50%"
    },
    "children": [
        "fontIconClose"
    ],
    "clipbounds": true,
    "containerId": true,
    "containerweight": 100,
    "desktopweb": {
        "psp": {
            "hoverSkin": "s54b03ed0af548f4b10ba6e76cf19723"
        }
    },
    "enablescrolling": true,
    "id": "flxClose",
    "ide_onClick": "AS_FlexContainer_d01abe772a6a4c09b140ae1057a7a0f2",
    "info": null,
    "isvisible": true,
    "kuid": "ed230a2eb87f49c9977712553b3b8c2e",
    "layouttype": 2,
    "name": "kony.ui.FlexContainer",
    "parent": "flxAddOptionWrapper",
    "pf": "segOptionAdded",
    "snapgridsize": 10,
    "snaptogrid": true,
    "wType": "FlexContainer",
    "widgetalignment": 1,
    "zindex": 1
}