{
    "@class": "com.kony.gen.viz.model.component.KVizButton",
    "DNDConfig": null,
    "_height_": {
        "type": "string",
        "value": "37dp"
    },
    "_left_": {
        "type": "string",
        "value": "30dp"
    },
    "_margin_": [
        6,
        6,
        6,
        6
    ],
    "_padding_": [
        0,
        0,
        0,
        0
    ],
    "_skin_": "se74dca26a744f03baf6ef97d48acf4b",
    "_text_": "",
    "_top_": {
        "type": "string",
        "value": "13dp"
    },
    "_width_": {
        "type": "string",
        "value": "85dp"
    },
    "canUpdateUI": true,
    "containerweight": 100,
    "contentalignment": 5,
    "disabledSkins": {
        "focusSkin": "s152a8ebff2840e2b2942e5ec1abbdb5"
    },
    "displaytext": true,
    "id": "btnPendingTab",
    "info": null,
    "isvisible": true,
    "kuid": "f8df50ee3ab948c48f95b47287bf7363",
    "name": "kony.ui.Button",
    "parent": "flxPendingSubmittedTabs",
    "pf": "frmLoansDashboard",
    "texti18n": "i18n.frmLoansDashboard.StartedApplication",
    "wType": "Button",
    "zindex": 5
}