{
    "@class": "com.kony.gen.viz.model.component.KVizListBox",
    "DNDConfig": null,
    "__parentReadjusting__": false,
    "_height_": {
        "type": "string",
        "value": "40dp"
    },
    "_left_": {
        "type": "string",
        "value": "0dp"
    },
    "_margin_": [
        0,
        0,
        0,
        0
    ],
    "_padding_": [
        3,
        0,
        0,
        0
    ],
    "_placeholder_": "Please Select",
    "_right_": {
        "type": "string",
        "value": "1dp"
    },
    "_skin_": "s99b746bd3eb4f598a3f966bd12deaa9",
    "_top_": {
        "type": "string",
        "value": "28dp"
    },
    "canUpdateUI": true,
    "containerweight": 100,
    "contentalignment": 4,
    "focusskin": "s8e2b9bc59214798999099f19e4148ae",
    "groupcells": false,
    "id": "lstBoxFrequencyCol3",
    "info": null,
    "iscustomlayout": false,
    "isvisible": true,
    "kuid": "gc78501cf138447e83c8356b25d7a99b",
    "masterdata": [
        [
            "SELECT",
            "Select a Day"
        ],
        [
            "MONDAY",
            "Monday"
        ],
        [
            "TUESDAY",
            "Tuesday"
        ],
        [
            "WEDNESDAY",
            "Wednesday"
        ],
        [
            "THURSDAY",
            "Thursday"
        ],
        [
            "FRIDAY",
            "Friday"
        ],
        [
            "SATURDAY",
            "Saturday"
        ],
        [
            "SUNDAY",
            "Sunday"
        ]
    ],
    "name": "kony.ui.ListBox",
    "parent": "flxFrequencyColumn3",
    "pf": "userwidgetmodel",
    "retaincontentalignment": false,
    "retainflexpositionproperties": false,
    "selectedkey": "SELECT",
    "selectedkeys": null,
    "selectedkeyvalue": null,
    "selectedkeyvalues": null,
    "size": 18,
    "viewconfig": {
        "toggleViewConfig": {
            "viewStyle": 0
        }
    },
    "viewtype": 0,
    "wType": "ListBox",
    "zindex": 1
}