{
    "DNDConfig": null,
    "_height_": {
        "type": "string",
        "value": "40dp"
    },
    "_left_": {
        "type": "string",
        "value": "10dp"
    },
    "_margin_": [
        0,
        0,
        0,
        0
    ],
    "_orientation_": 6,
    "_padding_": [
        0,
        0,
        0,
        0
    ],
    "_percent_": true,
    "_right_": {
        "type": "string",
        "value": "10dp"
    },
    "_skin_": "sb9d6e399da14265a46573f608f0a88f",
    "allboxes": [],
    "autogrowmode": 0,
    "canUpdateUI": true,
    "centery": {
        "type": "string",
        "value": "50%"
    },
    "children": [
        "fontIconExistingRolesSearchImg",
        "tbxExistingRolesSearchBox",
        "flxExistingRolesClearSearch"
    ],
    "clipbounds": true,
    "containerweight": 100,
    "desktopweb": {
        "psp": {}
    },
    "disabledSkins": {
        "focusSkin": "s85984211b6b4a518da4cc9a77aee487",
        "hoverSkin": "s85984211b6b4a518da4cc9a77aee487"
    },
    "enablescrolling": true,
    "focusskin": null,
    "id": "flxExistingRolesSearch",
    "info": null,
    "isvisible": true,
    "kuid": "c972b11093684019b4cc8b05d4081d9a",
    "layouttype": 2,
    "name": "kony.ui.FlexContainer",
    "parent": "flxExistingRolesSearchContainer",
    "pf": "frmAdDetails",
    "snapgridsize": 10,
    "snaptogrid": true,
    "wType": "FlexContainer",
    "widgetalignment": 1,
    "zindex": 1
}