{
    "AS_Form_i84b41a94cd94117916c0bb1a757bdca": {
        "id": "AS_Form_i84b41a94cd94117916c0bb1a757bdca",
        "type": "ACTION_SEQUENCE",
        "params": [{
            "datatype": "collection",
            "name": "eventobject"
        }],
        "contextObj": {
            "name": "frmTermsAndConditions",
            "type": "forms",
            "platform": null,
            "KUID": "h3d166746f0e4fa0acaa0b06870430d2"
        },
        "language": "js",
        "actions": [{
            "id": "ADD_SNIPPET_ide_preShow_bcc17701cb9d4270a1eb53580f7767dd",
            "type": "ADD_SNIPPET",
            "codeSnippet": "this.preShowActions();",
            "callbackType": null
        }]
    }
}